{
  "version": "5",
  "dialect": "mysql",
  "id": "4a959446-3365-4345-8c06-91fdd12dbba5",
  "prevId": "8339fbd0-11e4-4d93-8ed8-05567d2613e4",
  "tables": {
    "cities": {
      "name": "cities",
      "columns": {
        "id": {
          "name": "id",
          "type": "serial",
          "primaryKey": true,
          "notNull": true,
          "autoincrement": true
        },
        "name": {
          "name": "name",
          "type": "varchar(256)",
          "primaryKey": false,
          "notNull": false,
          "autoincrement": false
        },
        "popularity": {
          "name": "popularity",
          "type": "enum('unknown','known','popular')",
          "primaryKey": false,
          "notNull": false,
          "autoincrement": false
        }
      },
      "indexes": {},
      "foreignKeys": {},
      "compositePrimaryKeys": {}
    },
    "countries": {
      "name": "countries",
      "columns": {
        "id": {
          "name": "id",
          "type": "serial",
          "primaryKey": true,
          "notNull": true,
          "autoincrement": true
        },
        "name": {
          "name": "name",
          "type": "varchar(256)",
          "primaryKey": false,
          "notNull": false,
          "autoincrement": false
        }
      },
      "indexes": {
        "name_idx": {
          "name": "name_idx",
          "columns": [
            "name"
          ],
          "isUnique": true
        }
      },
      "foreignKeys": {},
      "compositePrimaryKeys": {}
    }
  },
  "schemas": {},
  "_meta": {
    "schemas": {},
    "tables": {},
    "columns": {}
  }
}